polyglot/.DS_Store
polyglot/.coverage
polyglot/__init__.py
polyglot/__version__.py
polyglot/cl_utils.py
polyglot/default_settings.yaml
polyglot/ebook.py
polyglot/htmlCleaner.py
polyglot/kindle.py
polyglot/printpdf.py
polyglot/utKit.py
polyglot/webarchive.py
polyglot/commonutils/__init__.py
polyglot/commonutils/getpackagepath.py
polyglot/css/.DS_Store
polyglot/css/config.codekit
polyglot/css/main.css
polyglot/css/main.scss
polyglot/css/.sass-cache/297a9a1db688d814ac7c92b8df06ebf07a767429/main.scssc
polyglot/markdown/__init__.py
polyglot/markdown/kindle_notebook.py
polyglot/markdown/translate.py
polyglot/markdown/tests/__init__.py
polyglot/markdown/tests/test_kindle_notebook.py
polyglot/markdown/tests/test_translate.py
polyglot/markdown/tests/input/How_Light_Works_xx1578xx_-_Notebook.html
polyglot/markdown/tests/input/Non-Kindle.html
polyglot/markdown/tests/input/example_settings.yaml
polyglot/markdown/tests/output/How_Light_Works.md
polyglot/markdown/tests/output/How_Light_Works_xx1578xx_-_Notebook.html
polyglot/markdown/tests/output/Non-Kindle.html
polyglot/markdown/tests/output/example_settings.yaml
polyglot/markdown/tests/output/markdown-output.md
polyglot/tests/__init__.py
polyglot/tests/test_ebook.py
polyglot/tests/test_htmlCleaner.py
polyglot/tests/test_kindle.py
polyglot/tests/test_print.py
polyglot/tests/test_webarchive.py
polyglot/tests/input/Localization.html
polyglot/tests/input/Volkswagen.docx
polyglot/tests/input/Volkswagen.epub
polyglot/tests/input/example_settings.yaml
polyglot/tests/output/Cars_original.pdf
polyglot/tests/output/Localization.html
polyglot/tests/output/Volkswagen.docx
polyglot/tests/output/Volkswagen.epub
polyglot/tests/output/Volkswagen.pdf
polyglot/tests/output/Volkswagen.webarchive
polyglot/tests/output/Volkswagen_original.pdf
polyglot/tests/output/example_settings.yaml
pypolyglot-1.0.1.dist-info/DESCRIPTION.rst
pypolyglot-1.0.1.dist-info/METADATA
pypolyglot-1.0.1.dist-info/RECORD
pypolyglot-1.0.1.dist-info/WHEEL
pypolyglot-1.0.1.dist-info/entry_points.txt
pypolyglot-1.0.1.dist-info/metadata.json
pypolyglot-1.0.1.dist-info/top_level.txt
