Metadata-Version: 2.0
Name: pypolyglot
Version: 1.0.1
Summary: Translate documents and webpages to various markup languages and document formats (html, epub, mobi ..)
Home-page: https://github.com/thespacedoctor/polyglot
Author: David Young
Author-email: davidrobertyoung@gmail.com
License: MIT
Download-URL: https://github.com/thespacedoctor/polyglot/archive/v1.0.1.zip
Keywords: pdf, html, parser
Platform: UNKNOWN
Classifier: Development Status :: 4 - Beta
Classifier: License :: OSI Approved :: MIT License
Classifier: Programming Language :: Python :: 2.7
Classifier: Topic :: Utilities
Requires-Dist: bs4
Requires-Dist: fundamentals
Requires-Dist: pypolyglot
Requires-Dist: pyyaml
Requires-Dist: requests
